pyinvoicer/__init__.py
pyinvoicer/invoice.py
pyinvoicer/item.py
pyinvoicer/pyinvoicer.py
pyinvoicer/renderer.py
pyinvoicer/templates/invoice.html
pyinvoicer/templates/styles.css
pyinvoicer-0.0.3.dist-info/entry_points.txt
pyinvoicer-0.0.3.dist-info/LICENSE
pyinvoicer-0.0.3.dist-info/WHEEL
pyinvoicer-0.0.3.dist-info/METADATA
pyinvoicer-0.0.3.dist-info/RECORD
